tex_fast_recompile/__init__.py
tex_fast_recompile/__main__.py
tex_fast_recompile/latexmk.py
tex_fast_recompile/util.py
tex_fast_recompile-0.5.2.dist-info/LICENSE
tex_fast_recompile-0.5.2.dist-info/METADATA
tex_fast_recompile-0.5.2.dist-info/WHEEL
tex_fast_recompile-0.5.2.dist-info/entry_points.txt
tex_fast_recompile-0.5.2.dist-info/top_level.txt
tex_fast_recompile-0.5.2.dist-info/RECORD
