Metadata-Version: 2.1
Name: tex-fast-recompile
Version: 0.5.2
Summary: A Python module to speed up TeX compilation.
Home-page: https://github.com/user202729/tex-fast-recompile
Author: user202729
License: LPPL 1.3c
Classifier: License :: OSI Approved
Classifier: Operating System :: OS Independent
Classifier: Programming Language :: Python :: 3
Classifier: Topic :: Text Processing :: Markup :: LaTeX
License-File: LICENSE
Requires-Dist: watchdog (~=2.1.2)
Requires-Dist: psutil (~=5.9.4)
